ipyvue_flatsurf/__init__.py
ipyvue_flatsurf/flatsurf.py
ipyvue_flatsurf/force_load.py
ipyvue_flatsurf/widget.py
ipyvue_flatsurf/encoding/__init__.py
ipyvue_flatsurf/encoding/flat_triangulation_encoding.py
ipyvue_flatsurf/encoding/flow_component_encoding.py
ipyvue_flatsurf/encoding/flow_decomposition_encoding.py
ipyvue_flatsurf/encoding/path_encoding.py
ipyvue_flatsurf/encoding/saddle_connection_encoding.py
ipyvue_flatsurf/labextension/package.json
ipyvue_flatsurf/labextension/static/214.65af76df6b73e49c843d.js
ipyvue_flatsurf/labextension/static/214.65af76df6b73e49c843d.js.LICENSE.txt
ipyvue_flatsurf/labextension/static/214.99c45e1825a2f3b1d95e.js
ipyvue_flatsurf/labextension/static/214.99c45e1825a2f3b1d95e.js.LICENSE.txt
ipyvue_flatsurf/labextension/static/24.7cc6fb35a588b58a3fb2.js
ipyvue_flatsurf/labextension/static/24.7cc6fb35a588b58a3fb2.js.LICENSE.txt
ipyvue_flatsurf/labextension/static/261.17a603d497b705637d58.js
ipyvue_flatsurf/labextension/static/261.272985dfb0fbdc6e2af5.js
ipyvue_flatsurf/labextension/static/261.2c5830f99e43a0e5a547.js
ipyvue_flatsurf/labextension/static/261.411ae9b15d46489799eb.js
ipyvue_flatsurf/labextension/static/261.affb4a45934f17e69938.js
ipyvue_flatsurf/labextension/static/261.b901e551adfabd5bd594.js
ipyvue_flatsurf/labextension/static/261.c0ecf3affb45c5b09b35.js
ipyvue_flatsurf/labextension/static/261.c1408eaacd1c2a543736.js
ipyvue_flatsurf/labextension/static/261.e6c8273c5401eb070444.js
ipyvue_flatsurf/labextension/static/261.e6f8021a02392f502330.js
ipyvue_flatsurf/labextension/static/261.f998ccedbe03bcc0d2a7.js
ipyvue_flatsurf/labextension/static/443.2777fe355650b8bbd32d.js
ipyvue_flatsurf/labextension/static/443.2777fe355650b8bbd32d.js.LICENSE.txt
ipyvue_flatsurf/labextension/static/443.58490bb33c6349d3bbc3.js
ipyvue_flatsurf/labextension/static/443.58490bb33c6349d3bbc3.js.LICENSE.txt
ipyvue_flatsurf/labextension/static/443.c370bbc056203b6bcfc0.js
ipyvue_flatsurf/labextension/static/443.c370bbc056203b6bcfc0.js.LICENSE.txt
ipyvue_flatsurf-0.6.3.dist-info/METADATA
ipyvue_flatsurf-0.6.3.dist-info/WHEEL
ipyvue_flatsurf-0.6.3.dist-info/top_level.txt
ipyvue_flatsurf-0.6.3.dist-info/RECORD
