Metadata-Version: 2.1
Name: ipyvue-flatsurf
Version: 0.6.3
Summary: Visualizations for Translations Surfaces in Jupyter Notebooks and JupyterLab
Home-page: https://github.com/flatsurf/ipyvue-flatsurf
Author: Julian Rüth
Author-email: julian.rueth@fsfe.org
Keywords: ipython,jupyter,widgets
Classifier: Development Status :: 4 - Beta
Classifier: Framework :: IPython
Classifier: License :: OSI Approved :: MIT License
Classifier: Intended Audience :: Developers
Classifier: Intended Audience :: Science/Research
Classifier: Topic :: Multimedia :: Graphics
Classifier: Programming Language :: Python :: 3.9
Classifier: Programming Language :: Python :: 3.10
Classifier: Programming Language :: Python :: 3.11
Classifier: Programming Language :: Python :: 3.12
Requires-Dist: ruamel.yaml <0.18,>=0.17.10
Requires-Dist: sage-flatsurf <0.8,>=0.5
Requires-Dist: pyflatsurf <4,>=3.9.0
Requires-Dist: jupyter-ui-poll <0.3,>=0.2.1
Requires-Dist: ipymuvue <0.7.0,>=0.3.0
